tumblr/__init__.py
tumblr/content.py
tumblr/tumblr.py
tumblrdotcom-0.3.3.dist-info/licenses/LICENSE
tumblrdotcom-0.3.3.dist-info/METADATA
tumblrdotcom-0.3.3.dist-info/WHEEL
tumblrdotcom-0.3.3.dist-info/top_level.txt
tumblrdotcom-0.3.3.dist-info/RECORD
