Metadata-Version: 2.4
Name: tumblrdotcom
Version: 0.3.3
Summary: Tumblr API wrapper with support for Polls
License-Expression: Apache-2.0
Project-URL: repository, https://codeberg.org/jamesansley/tumblrdotcom
Project-URL: documentation, https://tumblrdotcom.rtfd.io
Keywords: Tumblr,API
Requires-Python: >=3.11
License-File: LICENSE
Requires-Dist: requests>=2.31.0
Requires-Dist: requests-oauthlib>=1.3.1
Dynamic: license-file
